retorna_sdk/__init__.py
retorna_sdk/py.typed
retorna_sdk/account/__init__.py
retorna_sdk/account/account_client.py
retorna_sdk/client/__init__.py
retorna_sdk/client/builder.py
retorna_sdk/client/client.py
retorna_sdk/core/__init__.py
retorna_sdk/core/config/__init__.py
retorna_sdk/core/config/config.py
retorna_sdk/core/config/retry.py
retorna_sdk/core/credentials/__init__.py
retorna_sdk/core/credentials/auth_service.py
retorna_sdk/core/credentials/credentials.py
retorna_sdk/core/credentials/token_manager.py
retorna_sdk/core/credentials/utils.py
retorna_sdk/core/environment/__init__.py
retorna_sdk/core/environment/config.py
retorna_sdk/core/environment/resolver.py
retorna_sdk/core/environment/types.py
retorna_sdk/core/http/__init__.py
retorna_sdk/core/http/client.py
retorna_sdk/core/http/errors.py
retorna_sdk/core/http/signed_client.py
retorna_sdk/core/http/utils.py
retorna_sdk/core/logging/__init__.py
retorna_sdk/core/logging/config.py
retorna_sdk/core/logging/factory.py
retorna_sdk/core/logging/types.py
retorna_sdk/core/signature/__init__.py
retorna_sdk/core/signature/signature_service.py
retorna_sdk/core/signature/signer.py
retorna_sdk/core/signature/utils.py
retorna_sdk/models/__init__.py
retorna_sdk/models/payout_order/__init__.py
retorna_sdk/models/payout_order/payment_instructions.py
retorna_sdk/models/payout_order/payment_purpose.py
retorna_sdk/models/payout_order/payout_order.py
retorna_sdk/models/payout_order/payout_order_request.py
retorna_sdk/models/payout_order/validation/__init__.py
retorna_sdk/models/payout_order/validation/argentina.py
retorna_sdk/models/payout_order/validation/colombia.py
retorna_sdk/models/payout_order/validation/peru.py
retorna_sdk/models/payout_order/validation/registry.py
retorna_sdk/models/payout_order/validation/spain.py
retorna_sdk/models/payout_order/validation/usa.py
retorna_sdk/models/payout_order/validation/utils.py
retorna_sdk/models/payout_order/validation/venezuela.py
retorna_sdk/models/quotation/__init__.py
retorna_python_sdk-1.0.0.dist-info/METADATA
retorna_python_sdk-1.0.0.dist-info/WHEEL
retorna_python_sdk-1.0.0.dist-info/top_level.txt
retorna_python_sdk-1.0.0.dist-info/RECORD
