Metadata-Version: 2.4
Name: retorna-python-sdk
Version: 1.0.0
Summary: SDK de Retorna para Python que permite integrar pagos, cobros y servicios B2B.
Author: Retorna
Author-email: producto@retorna.app
Classifier: Programming Language :: Python :: 3
Requires-Python: >=3.9
Dynamic: author
Dynamic: author-email
Dynamic: classifier
Dynamic: description
Dynamic: description-content-type
Dynamic: requires-python
Dynamic: summary
